{
  "479.0": {
    "player_damage_taken": 123,
    "player_died": false,
    "player_level": 5,
    "player_hp_pct": 0.722,
    "player_incapacitated": true,
    "teammates_pos1": -1,
    "teammates_damage_taken_1": -1,
    "teammates_died_1": -1,
    "teammates_level_1": -1,
    "teammates_hp_pct_1": -1,
    "teammates_pos2": -1,
    "teammates_damage_taken_2": -1,
    "teammates_died_2": -1,
    "teammates_level_2": -1,
    "teammates_hp_pct_2": -1,
    "teammates_pos3": -1,
    "teammates_damage_taken_3": -1,
    "teammates_died_3": -1,
    "teammates_level_3": -1,
    "teammates_hp_pct_3": -1,
    "teammates_pos4": -1,
    "teammates_damage_taken_4": -1,
    "teammates_died_4": -1,
    "teammates_level_4": -1,
    "teammates_hp_pct_4": -1,
    "teammates_pos5": -1,
    "teammates_damage_taken_5": -1,
    "teammates_died_5": -1,
    "teammates_level_5": -1,
    "teammates_hp_pct_5": -1,
    "enemies_pos1": -1,
    "enemies_damage_taken_1": -1,
    "enemies_died_1": -1,
    "enemies_level_1": -1,
    "enemies_hp_pct_1": -1,
    "enemies_pos2": -1,
    "enemies_damage_taken_2": -1,
    "enemies_died_2": -1,
    "enemies_level_2": -1,
    "enemies_hp_pct_2": -1,
    "enemies_pos3": 4.59,
    "enemies_damage_taken_3": 0,
    "enemies_died_3": false,
    "enemies_level_3": 5,
    "enemies_hp_pct_3": 0.69,
    "enemies_pos4": 0.73,
    "enemies_damage_taken_4": 16,
    "enemies_died_4": false,
    "enemies_level_4": 5,
    "enemies_hp_pct_4": 0.849,
    "enemies_pos5": -1,
    "enemies_damage_taken_5": -1,
    "enemies_died_5": -1,
    "enemies_level_5": -1,
    "enemies_hp_pct_5": -1
  },
  "480.0": {
    "player_damage_taken": 111,
    "player_died": false,
    "player_level": 5,
    "player_hp_pct": 0.61,
    "player_incapacitated": true,
    "teammates_pos1": -1,
    "teammates_damage_taken_1": -1,
    "teammates_died_1": -1,
    "teammates_level_1": -1,
    "teammates_hp_pct_1": -1,
    "teammates_pos2": -1,
    "teammates_damage_taken_2": -1,
    "teammates_died_2": -1,
    "teammates_level_2": -1,
    "teammates_hp_pct_2": -1,
    "teammates_pos3": -1,
    "teammates_damage_taken_3": -1,
    "teammates_died_3": -1,
    "teammates_level_3": -1,
    "teammates_hp_pct_3": -1,
    "teammates_pos4": -1,
    "teammates_damage_taken_4": -1,
    "teammates_died_4": -1,
    "teammates_level_4": -1,
    "teammates_hp_pct_4": -1,
    "teammates_pos5": -1,
    "teammates_damage_taken_5": -1,
    "teammates_died_5": -1,
    "teammates_level_5": -1,
    "teammates_hp_pct_5": -1,
    "enemies_pos1": -1,
    "enemies_damage_taken_1": -1,
    "enemies_died_1": -1,
    "enemies_level_1": -1,
    "enemies_hp_pct_1": -1,
    "enemies_pos2": -1,
    "enemies_damage_taken_2": -1,
    "enemies_died_2": -1,
    "enemies_level_2": -1,
    "enemies_hp_pct_2": -1,
    "enemies_pos3": 3.5,
    "enemies_damage_taken_3": 0,
    "enemies_died_3": false,
    "enemies_level_3": 5,
    "enemies_hp_pct_3": 0.695,
    "enemies_pos4": 0.73,
    "enemies_damage_taken_4": 9,
    "enemies_died_4": false,
    "enemies_level_4": 5,
    "enemies_hp_pct_4": 0.832,
    "enemies_pos5": -1,
    "enemies_damage_taken_5": -1,
    "enemies_died_5": -1,
    "enemies_level_5": -1,
    "enemies_hp_pct_5": -1
  },
  "481.0": {
    "player_damage_taken": 32,
    "player_died": false,
    "player_level": 5,
    "player_hp_pct": 0.507,
    "player_incapacitated": true,
    "teammates_pos1": -1,
    "teammates_damage_taken_1": -1,
    "teammates_died_1": -1,
    "teammates_level_1": -1,
    "teammates_hp_pct_1": -1,
    "teammates_pos2": -1,
    "teammates_damage_taken_2": -1,
    "teammates_died_2": -1,
    "teammates_level_2": -1,
    "teammates_hp_pct_2": -1,
    "teammates_pos3": -1,
    "teammates_damage_taken_3": -1,
    "teammates_died_3": -1,
    "teammates_level_3": -1,
    "teammates_hp_pct_3": -1,
    "teammates_pos4": -1,
    "teammates_damage_taken_4": -1,
    "teammates_died_4": -1,
    "teammates_level_4": -1,
    "teammates_hp_pct_4": -1,
    "teammates_pos5": -1,
    "teammates_damage_taken_5": -1,
    "teammates_died_5": -1,
    "teammates_level_5": -1,
    "teammates_hp_pct_5": -1,
    "enemies_pos1": -1,
    "enemies_damage_taken_1": -1,
    "enemies_died_1": -1,
    "enemies_level_1": -1,
    "enemies_hp_pct_1": -1,
    "enemies_pos2": -1,
    "enemies_damage_taken_2": -1,
    "enemies_died_2": -1,
    "enemies_level_2": -1,
    "enemies_hp_pct_2": -1,
    "enemies_pos3": 3.5,
    "enemies_damage_taken_3": 8,
    "enemies_died_3": false,
    "enemies_level_3": 5,
    "enemies_hp_pct_3": 0.701,
    "enemies_pos4": 0.73,
    "enemies_damage_taken_4": 9,
    "enemies_died_4": false,
    "enemies_level_4": 5,
    "enemies_hp_pct_4": 0.824,
    "enemies_pos5": -1,
    "enemies_damage_taken_5": -1,
    "enemies_died_5": -1,
    "enemies_level_5": -1,
    "enemies_hp_pct_5": -1
  },
  "482.0": {
    "player_damage_taken": 107,
    "player_died": false,
    "player_level": 5,
    "player_hp_pct": 0.476,
    "player_incapacitated": true,
    "teammates_pos1": -1,
    "teammates_damage_taken_1": -1,
    "teammates_died_1": -1,
    "teammates_level_1": -1,
    "teammates_hp_pct_1": -1,
    "teammates_pos2": -1,
    "teammates_damage_taken_2": -1,
    "teammates_died_2": -1,
    "teammates_level_2": -1,
    "teammates_hp_pct_2": -1,
    "teammates_pos3": 3.77,
    "teammates_damage_taken_3": 0,
    "teammates_died_3": false,
    "teammates_level_3": 5,
    "teammates_hp_pct_3": 1.0,
    "teammates_pos4": -1,
    "teammates_damage_taken_4": -1,
    "teammates_died_4": -1,
    "teammates_level_4": -1,
    "teammates_hp_pct_4": -1,
    "teammates_pos5": -1,
    "teammates_damage_taken_5": -1,
    "teammates_died_5": -1,
    "teammates_level_5": -1,
    "teammates_hp_pct_5": -1,
    "enemies_pos1": -1,
    "enemies_damage_taken_1": -1,
    "enemies_died_1": -1,
    "enemies_level_1": -1,
    "enemies_hp_pct_1": -1,
    "enemies_pos2": -1,
    "enemies_damage_taken_2": -1,
    "enemies_died_2": -1,
    "enemies_level_2": -1,
    "enemies_hp_pct_2": -1,
    "enemies_pos3": 3.5,
    "enemies_damage_taken_3": 0,
    "enemies_died_3": false,
    "enemies_level_3": 5,
    "enemies_hp_pct_3": 0.763,
    "enemies_pos4": 0.49,
    "enemies_damage_taken_4": 0,
    "enemies_died_4": false,
    "enemies_level_4": 5,
    "enemies_hp_pct_4": 0.817,
    "enemies_pos5": -1,
    "enemies_damage_taken_5": -1,
    "enemies_died_5": -1,
    "enemies_level_5": -1,
    "enemies_hp_pct_5": -1
  },
  "483.0": {
    "player_damage_taken": 91,
    "player_died": false,
    "player_level": 5,
    "player_hp_pct": 0.375,
    "player_incapacitated": true,
    "teammates_pos1": -1,
    "teammates_damage_taken_1": -1,
    "teammates_died_1": -1,
    "teammates_level_1": -1,
    "teammates_hp_pct_1": -1,
    "teammates_pos2": -1,
    "teammates_damage_taken_2": -1,
    "teammates_died_2": -1,
    "teammates_level_2": -1,
    "teammates_hp_pct_2": -1,
    "teammates_pos3": 3.48,
    "teammates_damage_taken_3": 0,
    "teammates_died_3": false,
    "teammates_level_3": 5,
    "teammates_hp_pct_3": 1.0,
    "teammates_pos4": -1,
    "teammates_damage_taken_4": -1,
    "teammates_died_4": -1,
    "teammates_level_4": -1,
    "teammates_hp_pct_4": -1,
    "teammates_pos5": -1,
    "teammates_damage_taken_5": -1,
    "teammates_died_5": -1,
    "teammates_level_5": -1,
    "teammates_hp_pct_5": -1,
    "enemies_pos1": -1,
    "enemies_damage_taken_1": -1,
    "enemies_died_1": -1,
    "enemies_level_1": -1,
    "enemies_hp_pct_1": -1,
    "enemies_pos2": -1,
    "enemies_damage_taken_2": -1,
    "enemies_died_2": -1,
    "enemies_level_2": -1,
    "enemies_hp_pct_2": -1,
    "enemies_pos3": 3.5,
    "enemies_damage_taken_3": 247,
    "enemies_died_3": false,
    "enemies_level_3": 5,
    "enemies_hp_pct_3": 0.844,
    "enemies_pos4": 0.55,
    "enemies_damage_taken_4": 0,
    "enemies_died_4": false,
    "enemies_level_4": 5,
    "enemies_hp_pct_4": 0.822,
    "enemies_pos5": -1,
    "enemies_damage_taken_5": -1,
    "enemies_died_5": -1,
    "enemies_level_5": -1,
    "enemies_hp_pct_5": -1
  },
  "484.0": {
    "player_damage_taken": 92,
    "player_died": false,
    "player_level": 5,
    "player_hp_pct": 0.295,
    "player_incapacitated": true,
    "teammates_pos1": -1,
    "teammates_damage_taken_1": -1,
    "teammates_died_1": -1,
    "teammates_level_1": -1,
    "teammates_hp_pct_1": -1,
    "teammates_pos2": -1,
    "teammates_damage_taken_2": -1,
    "teammates_died_2": -1,
    "teammates_level_2": -1,
    "teammates_hp_pct_2": -1,
    "teammates_pos3": 3.43,
    "teammates_damage_taken_3": 0,
    "teammates_died_3": false,
    "teammates_level_3": 5,
    "teammates_hp_pct_3": 1.0,
    "teammates_pos4": -1,
    "teammates_damage_taken_4": -1,
    "teammates_died_4": -1,
    "teammates_level_4": -1,
    "teammates_hp_pct_4": -1,
    "teammates_pos5": -1,
    "teammates_damage_taken_5": -1,
    "teammates_died_5": -1,
    "teammates_level_5": -1,
    "teammates_hp_pct_5": -1,
    "enemies_pos1": -1,
    "enemies_damage_taken_1": -1,
    "enemies_died_1": -1,
    "enemies_level_1": -1,
    "enemies_hp_pct_1": -1,
    "enemies_pos2": -1,
    "enemies_damage_taken_2": -1,
    "enemies_died_2": -1,
    "enemies_level_2": -1,
    "enemies_hp_pct_2": -1,
    "enemies_pos3": 3.31,
    "enemies_damage_taken_3": 155,
    "enemies_died_3": false,
    "enemies_level_3": 5,
    "enemies_hp_pct_3": 0.546,
    "enemies_pos4": 0.55,
    "enemies_damage_taken_4": 188,
    "enemies_died_4": false,
    "enemies_level_4": 5,
    "enemies_hp_pct_4": 0.706,
    "enemies_pos5": -1,
    "enemies_damage_taken_5": -1,
    "enemies_died_5": -1,
    "enemies_level_5": -1,
    "enemies_hp_pct_5": -1
  },
  "485.0": {
    "player_damage_taken": 10,
    "player_died": false,
    "player_level": 5,
    "player_hp_pct": 0.212,
    "player_incapacitated": false,
    "teammates_pos1": -1,
    "teammates_damage_taken_1": -1,
    "teammates_died_1": -1,
    "teammates_level_1": -1,
    "teammates_hp_pct_1": -1,
    "teammates_pos2": -1,
    "teammates_damage_taken_2": -1,
    "teammates_died_2": -1,
    "teammates_level_2": -1,
    "teammates_hp_pct_2": -1,
    "teammates_pos3": 3.43,
    "teammates_damage_taken_3": 0,
    "teammates_died_3": false,
    "teammates_level_3": 5,
    "teammates_hp_pct_3": 1.0,
    "teammates_pos4": -1,
    "teammates_damage_taken_4": -1,
    "teammates_died_4": -1,
    "teammates_level_4": -1,
    "teammates_hp_pct_4": -1,
    "teammates_pos5": -1,
    "teammates_damage_taken_5": -1,
    "teammates_died_5": -1,
    "teammates_level_5": -1,
    "teammates_hp_pct_5": -1,
    "enemies_pos1": -1,
    "enemies_damage_taken_1": -1,
    "enemies_died_1": -1,
    "enemies_level_1": -1,
    "enemies_hp_pct_1": -1,
    "enemies_pos2": -1,
    "enemies_damage_taken_2": -1,
    "enemies_died_2": -1,
    "enemies_level_2": -1,
    "enemies_hp_pct_2": -1,
    "enemies_pos3": 3.31,
    "enemies_damage_taken_3": 87,
    "enemies_died_3": false,
    "enemies_level_3": 5,
    "enemies_hp_pct_3": 0.346,
    "enemies_pos4": 0.55,
    "enemies_damage_taken_4": 47,
    "enemies_died_4": false,
    "enemies_level_4": 5,
    "enemies_hp_pct_4": 0.59,
    "enemies_pos5": -1,
    "enemies_damage_taken_5": -1,
    "enemies_died_5": -1,
    "enemies_level_5": -1,
    "enemies_hp_pct_5": -1
  },
  "486.0": {
    "player_damage_taken": 56,
    "player_died": false,
    "player_level": 5,
    "player_hp_pct": 0.356,
    "player_incapacitated": false,
    "teammates_pos1": -1,
    "teammates_damage_taken_1": -1,
    "teammates_died_1": -1,
    "teammates_level_1": -1,
    "teammates_hp_pct_1": -1,
    "teammates_pos2": -1,
    "teammates_damage_taken_2": -1,
    "teammates_died_2": -1,
    "teammates_level_2": -1,
    "teammates_hp_pct_2": -1,
    "teammates_pos3": 3.24,
    "teammates_damage_taken_3": 0,
    "teammates_died_3": false,
    "teammates_level_3": 5,
    "teammates_hp_pct_3": 1.0,
    "teammates_pos4": -1,
    "teammates_damage_taken_4": -1,
    "teammates_died_4": -1,
    "teammates_level_4": -1,
    "teammates_hp_pct_4": -1,
    "teammates_pos5": -1,
    "teammates_damage_taken_5": -1,
    "teammates_died_5": -1,
    "teammates_level_5": -1,
    "teammates_hp_pct_5": -1,
    "enemies_pos1": -1,
    "enemies_damage_taken_1": -1,
    "enemies_died_1": -1,
    "enemies_level_1": -1,
    "enemies_hp_pct_1": -1,
    "enemies_pos2": -1,
    "enemies_damage_taken_2": -1,
    "enemies_died_2": -1,
    "enemies_level_2": -1,
    "enemies_hp_pct_2": -1,
    "enemies_pos3": 3.04,
    "enemies_damage_taken_3": 96,
    "enemies_died_3": false,
    "enemies_level_3": 5,
    "enemies_hp_pct_3": 0.373,
    "enemies_pos4": 1.1,
    "enemies_damage_taken_4": 91,
    "enemies_died_4": false,
    "enemies_level_4": 5,
    "enemies_hp_pct_4": 0.533,
    "enemies_pos5": -1,
    "enemies_damage_taken_5": -1,
    "enemies_died_5": -1,
    "enemies_level_5": -1,
    "enemies_hp_pct_5": -1
  },
  "487.0": {
    "player_damage_taken": 44,
    "player_died": false,
    "player_level": 5,
    "player_hp_pct": 0.431,
    "player_incapacitated": false,
    "teammates_pos1": -1,
    "teammates_damage_taken_1": -1,
    "teammates_died_1": -1,
    "teammates_level_1": -1,
    "teammates_hp_pct_1": -1,
    "teammates_pos2": -1,
    "teammates_damage_taken_2": -1,
    "teammates_died_2": -1,
    "teammates_level_2": -1,
    "teammates_hp_pct_2": -1,
    "teammates_pos3": 3.07,
    "teammates_damage_taken_3": 0,
    "teammates_died_3": false,
    "teammates_level_3": 5,
    "teammates_hp_pct_3": 1.0,
    "teammates_pos4": -1,
    "teammates_damage_taken_4": -1,
    "teammates_died_4": -1,
    "teammates_level_4": -1,
    "teammates_hp_pct_4": -1,
    "teammates_pos5": -1,
    "teammates_damage_taken_5": -1,
    "teammates_died_5": -1,
    "teammates_level_5": -1,
    "teammates_hp_pct_5": -1,
    "enemies_pos1": -1,
    "enemies_damage_taken_1": -1,
    "enemies_died_1": -1,
    "enemies_level_1": -1,
    "enemies_hp_pct_1": -1,
    "enemies_pos2": -1,
    "enemies_damage_taken_2": -1,
    "enemies_died_2": -1,
    "enemies_level_2": -1,
    "enemies_hp_pct_2": -1,
    "enemies_pos3": 3.62,
    "enemies_damage_taken_3": 0,
    "enemies_died_3": false,
    "enemies_level_3": 5,
    "enemies_hp_pct_3": 0.251,
    "enemies_pos4": 1.33,
    "enemies_damage_taken_4": 57,
    "enemies_died_4": false,
    "enemies_level_4": 5,
    "enemies_hp_pct_4": 0.421,
    "enemies_pos5": -1,
    "enemies_damage_taken_5": -1,
    "enemies_died_5": -1,
    "enemies_level_5": -1,
    "enemies_hp_pct_5": -1
  },
  "488.0": {
    "player_damage_taken": 21,
    "player_died": false,
    "player_level": 5,
    "player_hp_pct": 0.395,
    "player_incapacitated": false,
    "teammates_pos1": -1,
    "teammates_damage_taken_1": -1,
    "teammates_died_1": -1,
    "teammates_level_1": -1,
    "teammates_hp_pct_1": -1,
    "teammates_pos2": -1,
    "teammates_damage_taken_2": -1,
    "teammates_died_2": -1,
    "teammates_level_2": -1,
    "teammates_hp_pct_2": -1,
    "teammates_pos3": 3.42,
    "teammates_damage_taken_3": 0,
    "teammates_died_3": false,
    "teammates_level_3": 5,
    "teammates_hp_pct_3": 1.0,
    "teammates_pos4": -1,
    "teammates_damage_taken_4": -1,
    "teammates_died_4": -1,
    "teammates_level_4": -1,
    "teammates_hp_pct_4": -1,
    "teammates_pos5": -1,
    "teammates_damage_taken_5": -1,
    "teammates_died_5": -1,
    "teammates_level_5": -1,
    "teammates_hp_pct_5": -1,
    "enemies_pos1": -1,
    "enemies_damage_taken_1": -1,
    "enemies_died_1": -1,
    "enemies_level_1": -1,
    "enemies_hp_pct_1": -1,
    "enemies_pos2": -1,
    "enemies_damage_taken_2": -1,
    "enemies_died_2": -1,
    "enemies_level_2": -1,
    "enemies_hp_pct_2": -1,
    "enemies_pos3": 5.21,
    "enemies_damage_taken_3": 0,
    "enemies_died_3": false,
    "enemies_level_3": 5,
    "enemies_hp_pct_3": 0.256,
    "enemies_pos4": 2.44,
    "enemies_damage_taken_4": 96,
    "enemies_died_4": false,
    "enemies_level_4": 5,
    "enemies_hp_pct_4": 0.277,
    "enemies_pos5": -1,
    "enemies_damage_taken_5": -1,
    "enemies_died_5": -1,
    "enemies_level_5": -1,
    "enemies_hp_pct_5": -1
  },
  "489.0": {
    "player_damage_taken": 10,
    "player_died": false,
    "player_level": 5,
    "player_hp_pct": 0.382,
    "player_incapacitated": false,
    "teammates_pos1": -1,
    "teammates_damage_taken_1": -1,
    "teammates_died_1": -1,
    "teammates_level_1": -1,
    "teammates_hp_pct_1": -1,
    "teammates_pos2": -1,
    "teammates_damage_taken_2": -1,
    "teammates_died_2": -1,
    "teammates_level_2": -1,
    "teammates_hp_pct_2": -1,
    "teammates_pos3": 4.22,
    "teammates_damage_taken_3": 0,
    "teammates_died_3": false,
    "teammates_level_3": 5,
    "teammates_hp_pct_3": 1.0,
    "teammates_pos4": -1,
    "teammates_damage_taken_4": -1,
    "teammates_died_4": -1,
    "teammates_level_4": -1,
    "teammates_hp_pct_4": -1,
    "teammates_pos5": -1,
    "teammates_damage_taken_5": -1,
    "teammates_died_5": -1,
    "teammates_level_5": -1,
    "teammates_hp_pct_5": -1,
    "enemies_pos1": -1,
    "enemies_damage_taken_1": -1,
    "enemies_died_1": -1,
    "enemies_level_1": -1,
    "enemies_hp_pct_1": -1,
    "enemies_pos2": -1,
    "enemies_damage_taken_2": -1,
    "enemies_died_2": -1,
    "enemies_level_2": -1,
    "enemies_hp_pct_2": -1,
    "enemies_pos3": 6.45,
    "enemies_damage_taken_3": 0,
    "enemies_died_3": false,
    "enemies_level_3": 5,
    "enemies_hp_pct_3": 0.261,
    "enemies_pos4": 2.61,
    "enemies_damage_taken_4": 29,
    "enemies_died_4": false,
    "enemies_level_4": 5,
    "enemies_hp_pct_4": 0.232,
    "enemies_pos5": -1,
    "enemies_damage_taken_5": -1,
    "enemies_died_5": -1,
    "enemies_level_5": -1,
    "enemies_hp_pct_5": -1
  },
  "490.0": {
    "player_damage_taken": 92,
    "player_died": false,
    "player_level": 5,
    "player_hp_pct": 0.381,
    "player_incapacitated": false,
    "teammates_pos1": -1,
    "teammates_damage_taken_1": -1,
    "teammates_died_1": -1,
    "teammates_level_1": -1,
    "teammates_hp_pct_1": -1,
    "teammates_pos2": -1,
    "teammates_damage_taken_2": -1,
    "teammates_died_2": -1,
    "teammates_level_2": -1,
    "teammates_hp_pct_2": -1,
    "teammates_pos3": 7.79,
    "teammates_damage_taken_3": 9,
    "teammates_died_3": false,
    "teammates_level_3": 5,
    "teammates_hp_pct_3": 1.0,
    "teammates_pos4": -1,
    "teammates_damage_taken_4": -1,
    "teammates_died_4": -1,
    "teammates_level_4": -1,
    "teammates_hp_pct_4": -1,
    "teammates_pos5": -1,
    "teammates_damage_taken_5": -1,
    "teammates_died_5": -1,
    "teammates_level_5": -1,
    "teammates_hp_pct_5": -1,
    "enemies_pos1": -1,
    "enemies_damage_taken_1": -1,
    "enemies_died_1": -1,
    "enemies_level_1": -1,
    "enemies_hp_pct_1": -1,
    "enemies_pos2": -1,
    "enemies_damage_taken_2": -1,
    "enemies_died_2": -1,
    "enemies_level_2": -1,
    "enemies_hp_pct_2": -1,
    "enemies_pos3": 8.79,
    "enemies_damage_taken_3": 68,
    "enemies_died_3": false,
    "enemies_level_3": 5,
    "enemies_hp_pct_3": 0.266,
    "enemies_pos4": 2.17,
    "enemies_damage_taken_4": 86,
    "enemies_died_4": false,
    "enemies_level_4": 5,
    "enemies_hp_pct_4": 0.2,
    "enemies_pos5": -1,
    "enemies_damage_taken_5": -1,
    "enemies_died_5": -1,
    "enemies_level_5": -1,
    "enemies_hp_pct_5": -1
  },
  "491.0": {
    "player_damage_taken": 126,
    "player_died": false,
    "player_level": 5,
    "player_hp_pct": 0.297,
    "player_incapacitated": false,
    "teammates_pos1": -1,
    "teammates_damage_taken_1": -1,
    "teammates_died_1": -1,
    "teammates_level_1": -1,
    "teammates_hp_pct_1": -1,
    "teammates_pos2": -1,
    "teammates_damage_taken_2": -1,
    "teammates_died_2": -1,
    "teammates_level_2": -1,
    "teammates_hp_pct_2": -1,
    "teammates_pos3": 9.39,
    "teammates_damage_taken_3": 0,
    "teammates_died_3": false,
    "teammates_level_3": 5,
    "teammates_hp_pct_3": 0.995,
    "teammates_pos4": -1,
    "teammates_damage_taken_4": -1,
    "teammates_died_4": -1,
    "teammates_level_4": -1,
    "teammates_hp_pct_4": -1,
    "teammates_pos5": -1,
    "teammates_damage_taken_5": -1,
    "teammates_died_5": -1,
    "teammates_level_5": -1,
    "teammates_hp_pct_5": -1,
    "enemies_pos1": -1,
    "enemies_damage_taken_1": -1,
    "enemies_died_1": -1,
    "enemies_level_1": -1,
    "enemies_hp_pct_1": -1,
    "enemies_pos2": -1,
    "enemies_damage_taken_2": -1,
    "enemies_died_2": -1,
    "enemies_level_2": -1,
    "enemies_hp_pct_2": -1,
    "enemies_pos3": 8.75,
    "enemies_damage_taken_3": 0,
    "enemies_died_3": false,
    "enemies_level_3": 5,
    "enemies_hp_pct_3": 0.182,
    "enemies_pos4": 0.44,
    "enemies_damage_taken_4": 75,
    "enemies_died_4": false,
    "enemies_level_4": 5,
    "enemies_hp_pct_4": 0.094,
    "enemies_pos5": -1,
    "enemies_damage_taken_5": -1,
    "enemies_died_5": -1,
    "enemies_level_5": -1,
    "enemies_hp_pct_5": -1
  },
  "492.0": {
    "player_damage_taken": 132,
    "player_died": false,
    "player_level": 5,
    "player_hp_pct": 0.179,
    "player_incapacitated": false,
    "teammates_pos1": -1,
    "teammates_damage_taken_1": -1,
    "teammates_died_1": -1,
    "teammates_level_1": -1,
    "teammates_hp_pct_1": -1,
    "teammates_pos2": -1,
    "teammates_damage_taken_2": -1,
    "teammates_died_2": -1,
    "teammates_level_2": -1,
    "teammates_hp_pct_2": -1,
    "teammates_pos3": 8.95,
    "teammates_damage_taken_3": 0,
    "teammates_died_3": false,
    "teammates_level_3": 5,
    "teammates_hp_pct_3": 1.0,
    "teammates_pos4": -1,
    "teammates_damage_taken_4": -1,
    "teammates_died_4": -1,
    "teammates_level_4": -1,
    "teammates_hp_pct_4": -1,
    "teammates_pos5": -1,
    "teammates_damage_taken_5": -1,
    "teammates_died_5": -1,
    "teammates_level_5": -1,
    "teammates_hp_pct_5": -1,
    "enemies_pos1": -1,
    "enemies_damage_taken_1": -1,
    "enemies_died_1": -1,
    "enemies_level_1": -1,
    "enemies_hp_pct_1": -1,
    "enemies_pos2": -1,
    "enemies_damage_taken_2": -1,
    "enemies_died_2": -1,
    "enemies_level_2": -1,
    "enemies_hp_pct_2": -1,
    "enemies_pos3": 10.81,
    "enemies_damage_taken_3": 0,
    "enemies_died_3": false,
    "enemies_level_3": 5,
    "enemies_hp_pct_3": 0.187,
    "enemies_pos4": 0.42,
    "enemies_damage_taken_4": 29,
    "enemies_died_4": false,
    "enemies_level_4": 5,
    "enemies_hp_pct_4": 0.156,
    "enemies_pos5": -1,
    "enemies_damage_taken_5": -1,
    "enemies_died_5": -1,
    "enemies_level_5": -1,
    "enemies_hp_pct_5": -1
  },
  "493.0": {
    "player_damage_taken": 66,
    "player_died": true,
    "player_level": 5,
    "player_hp_pct": 0.057,
    "player_incapacitated": false,
    "teammates_pos1": -1,
    "teammates_damage_taken_1": -1,
    "teammates_died_1": -1,
    "teammates_level_1": -1,
    "teammates_hp_pct_1": -1,
    "teammates_pos2": -1,
    "teammates_damage_taken_2": -1,
    "teammates_died_2": -1,
    "teammates_level_2": -1,
    "teammates_hp_pct_2": -1,
    "teammates_pos3": 10.09,
    "teammates_damage_taken_3": 0,
    "teammates_died_3": false,
    "teammates_level_3": 5,
    "teammates_hp_pct_3": 1.0,
    "teammates_pos4": -1,
    "teammates_damage_taken_4": -1,
    "teammates_died_4": -1,
    "teammates_level_4": -1,
    "teammates_hp_pct_4": -1,
    "teammates_pos5": -1,
    "teammates_damage_taken_5": -1,
    "teammates_died_5": -1,
    "teammates_level_5": -1,
    "teammates_hp_pct_5": -1,
    "enemies_pos1": -1,
    "enemies_damage_taken_1": -1,
    "enemies_died_1": -1,
    "enemies_level_1": -1,
    "enemies_hp_pct_1": -1,
    "enemies_pos2": -1,
    "enemies_damage_taken_2": -1,
    "enemies_died_2": -1,
    "enemies_level_2": -1,
    "enemies_hp_pct_2": -1,
    "enemies_pos3": 11.46,
    "enemies_damage_taken_3": 0,
    "enemies_died_3": false,
    "enemies_level_3": 5,
    "enemies_hp_pct_3": 0.193,
    "enemies_pos4": 0.42,
    "enemies_damage_taken_4": 57,
    "enemies_died_4": false,
    "enemies_level_4": 5,
    "enemies_hp_pct_4": 0.124,
    "enemies_pos5": -1,
    "enemies_damage_taken_5": -1,
    "enemies_died_5": -1,
    "enemies_level_5": -1,
    "enemies_hp_pct_5": -1
  },
  "494.0": {
    "player_damage_taken": 0,
    "player_died": false,
    "player_level": 5,
    "player_hp_pct": 0.0,
    "player_incapacitated": false,
    "teammates_pos1": -1,
    "teammates_damage_taken_1": -1,
    "teammates_died_1": -1,
    "teammates_level_1": -1,
    "teammates_hp_pct_1": -1,
    "teammates_pos2": -1,
    "teammates_damage_taken_2": -1,
    "teammates_died_2": -1,
    "teammates_level_2": -1,
    "teammates_hp_pct_2": -1,
    "teammates_pos3": 10.71,
    "teammates_damage_taken_3": 0,
    "teammates_died_3": false,
    "teammates_level_3": 5,
    "teammates_hp_pct_3": 1.0,
    "teammates_pos4": -1,
    "teammates_damage_taken_4": -1,
    "teammates_died_4": -1,
    "teammates_level_4": -1,
    "teammates_hp_pct_4": -1,
    "teammates_pos5": -1,
    "teammates_damage_taken_5": -1,
    "teammates_died_5": -1,
    "teammates_level_5": -1,
    "teammates_hp_pct_5": -1,
    "enemies_pos1": -1,
    "enemies_damage_taken_1": -1,
    "enemies_died_1": -1,
    "enemies_level_1": -1,
    "enemies_hp_pct_1": -1,
    "enemies_pos2": -1,
    "enemies_damage_taken_2": -1,
    "enemies_died_2": -1,
    "enemies_level_2": -1,
    "enemies_hp_pct_2": -1,
    "enemies_pos3": 12.55,
    "enemies_damage_taken_3": 73,
    "enemies_died_3": false,
    "enemies_level_3": 6,
    "enemies_hp_pct_3": 0.198,
    "enemies_pos4": 0.78,
    "enemies_damage_taken_4": 0,
    "enemies_died_4": false,
    "enemies_level_4": 5,
    "enemies_hp_pct_4": 0.055,
    "enemies_pos5": -1,
    "enemies_damage_taken_5": -1,
    "enemies_died_5": -1,
    "enemies_level_5": -1,
    "enemies_hp_pct_5": -1
  }
}