{
  "1460.0": {
    "player_pos": [
      0.0,
      0.0
    ],
    "teammates_pos": [
      [
        17.1,
        -2.54
      ],
      [
        0.53,
        0.85
      ]
    ],
    "enemies_pos": [
      [
        -9.8,
        14.99
      ],
      [
        -15.64,
        8.28
      ]
    ],
    "player_damage_taken": 0,
    "player_died": false,
    "player_level": 15,
    "player_hp_pct": 1.0,
    "teammates_levels": [
      15,
      15
    ],
    "enemies_levels": [
      11,
      12
    ],
    "teammates_damage_taken": [
      0,
      0
    ],
    "enemies_damage_taken": [
      0,
      0
    ],
    "teammates_died": [
      false,
      false
    ],
    "enemies_died": [
      false,
      false
    ],
    "teammates_hp_pct": [
      1.0,
      1.0
    ],
    "enemies_hp_pct": [
      1.0,
      1.0
    ]
  },
  "1461.0": {
    "player_pos": [
      0.0,
      0.0
    ],
    "teammates_pos": [
      [
        17.23,
        -5.64
      ],
      [
        4.72,
        -1.41
      ]
    ],
    "enemies_pos": [
      [
        -6.49,
        12.77
      ],
      [
        -14.07,
        8.61
      ]
    ],
    "player_damage_taken": 0,
    "player_died": false,
    "player_level": 15,
    "player_hp_pct": 1.0,
    "teammates_levels": [
      15,
      15
    ],
    "enemies_levels": [
      11,
      12
    ],
    "teammates_damage_taken": [
      0,
      0
    ],
    "enemies_damage_taken": [
      0,
      0
    ],
    "teammates_died": [
      false,
      false
    ],
    "enemies_died": [
      false,
      false
    ],
    "teammates_hp_pct": [
      1.0,
      1.0
    ],
    "enemies_hp_pct": [
      1.0,
      1.0
    ]
  },
  "1462.0": {
    "player_pos": [
      0.0,
      0.0
    ],
    "teammates_pos": [
      [
        16.61,
        -7.3
      ],
      [
        5.95,
        -1.88
      ],
      [
        -2.4,
        18.52
      ]
    ],
    "enemies_pos": [
      [
        -2.16,
        11.53
      ],
      [
        -10.1,
        9.84
      ]
    ],
    "player_damage_taken": 0,
    "player_died": false,
    "player_level": 15,
    "player_hp_pct": 1.0,
    "teammates_levels": [
      15,
      15,
      15
    ],
    "enemies_levels": [
      11,
      12
    ],
    "teammates_damage_taken": [
      0,
      0,
      0
    ],
    "enemies_damage_taken": [
      0,
      0
    ],
    "teammates_died": [
      false,
      false,
      false
    ],
    "enemies_died": [
      false,
      false
    ],
    "teammates_hp_pct": [
      1.0,
      1.0,
      1.0
    ],
    "enemies_hp_pct": [
      1.0,
      1.0
    ]
  },
  "1463.0": {
    "player_pos": [
      0.0,
      0.0
    ],
    "teammates_pos": [
      [
        15.67,
        -8.15
      ],
      [
        6.35,
        -1.07
      ],
      [
        1.83,
        15.67
      ]
    ],
    "enemies_pos": [
      [
        1.54,
        11.24
      ],
      [
        -6.08,
        10.89
      ]
    ],
    "player_damage_taken": 0,
    "player_died": false,
    "player_level": 15,
    "player_hp_pct": 1.0,
    "teammates_levels": [
      15,
      15,
      15
    ],
    "enemies_levels": [
      11,
      12
    ],
    "teammates_damage_taken": [
      0,
      0,
      0
    ],
    "enemies_damage_taken": [
      0,
      0
    ],
    "teammates_died": [
      false,
      false,
      false
    ],
    "enemies_died": [
      false,
      false
    ],
    "teammates_hp_pct": [
      1.0,
      1.0,
      1.0
    ],
    "enemies_hp_pct": [
      1.0,
      1.0
    ]
  },
  "1464.0": {
    "player_pos": [
      0.0,
      0.0
    ],
    "teammates_pos": [
      [
        12.61,
        -9.82
      ],
      [
        4.89,
        -1.52
      ],
      [
        3.76,
        11.23
      ]
    ],
    "enemies_pos": [
      [
        2.98,
        8.31
      ],
      [
        -4.44,
        8.04
      ]
    ],
    "player_damage_taken": 0,
    "player_died": false,
    "player_level": 15,
    "player_hp_pct": 1.0,
    "teammates_levels": [
      15,
      15,
      15
    ],
    "enemies_levels": [
      11,
      12
    ],
    "teammates_damage_taken": [
      0,
      0,
      0
    ],
    "enemies_damage_taken": [
      0,
      0
    ],
    "teammates_died": [
      false,
      false,
      false
    ],
    "enemies_died": [
      false,
      false
    ],
    "teammates_hp_pct": [
      1.0,
      1.0,
      1.0
    ],
    "enemies_hp_pct": [
      1.0,
      1.0
    ]
  },
  "1465.0": {
    "player_pos": [
      0.0,
      0.0
    ],
    "teammates_pos": [
      [
        10.36,
        -10.0
      ],
      [
        3.81,
        -3.0
      ],
      [
        5.95,
        8.05
      ]
    ],
    "enemies_pos": [
      [
        4.48,
        7.33
      ],
      [
        -1.96,
        4.51
      ]
    ],
    "player_damage_taken": 0,
    "player_died": false,
    "player_level": 15,
    "player_hp_pct": 1.0,
    "teammates_levels": [
      15,
      15,
      15
    ],
    "enemies_levels": [
      11,
      12
    ],
    "teammates_damage_taken": [
      0,
      0,
      0
    ],
    "enemies_damage_taken": [
      0,
      0
    ],
    "teammates_died": [
      false,
      false,
      false
    ],
    "enemies_died": [
      false,
      false
    ],
    "teammates_hp_pct": [
      1.0,
      1.0,
      1.0
    ],
    "enemies_hp_pct": [
      1.0,
      1.0
    ]
  },
  "1466.0": {
    "player_pos": [
      0.0,
      0.0
    ],
    "teammates_pos": [
      [
        8.35,
        -7.85
      ],
      [
        2.61,
        -3.15
      ],
      [
        7.1,
        8.18
      ]
    ],
    "enemies_pos": [
      [
        3.65,
        9.8
      ],
      [
        -1.96,
        4.51
      ]
    ],
    "player_damage_taken": 0,
    "player_died": false,
    "player_level": 15,
    "player_hp_pct": 1.0,
    "teammates_levels": [
      15,
      15,
      15
    ],
    "enemies_levels": [
      11,
      12
    ],
    "teammates_damage_taken": [
      0,
      0,
      0
    ],
    "enemies_damage_taken": [
      0,
      0
    ],
    "teammates_died": [
      false,
      false,
      false
    ],
    "enemies_died": [
      false,
      false
    ],
    "teammates_hp_pct": [
      1.0,
      1.0,
      1.0
    ],
    "enemies_hp_pct": [
      1.0,
      1.0
    ]
  },
  "1467.0": {
    "player_pos": [
      0.0,
      0.0
    ],
    "teammates_pos": [
      [
        6.76,
        -5.44
      ],
      [
        1.21,
        -2.18
      ],
      [
        5.32,
        6.05
      ]
    ],
    "enemies_pos": [
      [
        2.03,
        8.86
      ],
      [
        -1.96,
        4.51
      ]
    ],
    "player_damage_taken": 245,
    "player_died": false,
    "player_level": 15,
    "player_hp_pct": 1.0,
    "teammates_levels": [
      15,
      15,
      15
    ],
    "enemies_levels": [
      11,
      12
    ],
    "teammates_damage_taken": [
      0,
      274,
      0
    ],
    "enemies_damage_taken": [
      0,
      0
    ],
    "teammates_died": [
      false,
      false,
      false
    ],
    "enemies_died": [
      false,
      false
    ],
    "teammates_hp_pct": [
      1.0,
      1.0,
      1.0
    ],
    "enemies_hp_pct": [
      1.0,
      1.0
    ]
  },
  "1468.0": {
    "player_pos": [
      0.0,
      0.0
    ],
    "teammates_pos": [
      [
        5.55,
        -3.14
      ],
      [
        0.21,
        -1.67
      ],
      [
        3.83,
        3.72
      ]
    ],
    "enemies_pos": [
      [
        1.64,
        8.36
      ],
      [
        -1.96,
        4.51
      ]
    ],
    "player_damage_taken": 33,
    "player_died": false,
    "player_level": 15,
    "player_hp_pct": 0.831,
    "teammates_levels": [
      15,
      15,
      15
    ],
    "enemies_levels": [
      11,
      12
    ],
    "teammates_damage_taken": [
      290,
      0,
      0
    ],
    "enemies_damage_taken": [
      0,
      206
    ],
    "teammates_died": [
      false,
      false,
      false
    ],
    "enemies_died": [
      false,
      false
    ],
    "teammates_hp_pct": [
      1.0,
      0.887,
      1.0
    ],
    "enemies_hp_pct": [
      1.0,
      1.0
    ]
  },
  "1469.0": {
    "player_pos": [
      0.0,
      0.0
    ],
    "teammates_pos": [
      [
        7.45,
        -2.68
      ],
      [
        -1.23,
        -0.24
      ],
      [
        3.5,
        3.83
      ]
    ],
    "enemies_pos": [
      [
        2.05,
        9.16
      ],
      [
        -10.05,
        -17.16
      ],
      [
        -1.44,
        5.94
      ]
    ],
    "player_damage_taken": 607,
    "player_died": false,
    "player_level": 15,
    "player_hp_pct": 0.836,
    "teammates_levels": [
      15,
      15,
      15
    ],
    "enemies_levels": [
      11,
      17,
      12
    ],
    "teammates_damage_taken": [
      0,
      0,
      0
    ],
    "enemies_damage_taken": [
      0,
      0,
      0
    ],
    "teammates_died": [
      false,
      false,
      false
    ],
    "enemies_died": [
      false,
      false,
      false
    ],
    "teammates_hp_pct": [
      0.903,
      0.893,
      1.0
    ],
    "enemies_hp_pct": [
      1.0,
      1.0,
      0.874
    ]
  },
  "1470.0": {
    "player_pos": [
      0.0,
      0.0
    ],
    "teammates_pos": [
      [
        6.0,
        -0.55
      ],
      [
        -2.59,
        2.28
      ],
      [
        -14.32,
        -5.55
      ],
      [
        5.22,
        5.92
      ]
    ],
    "enemies_pos": [
      [
        1.98,
        10.94
      ],
      [
        -7.49,
        -12.85
      ],
      [
        -0.38,
        9.4
      ]
    ],
    "player_damage_taken": 293,
    "player_died": false,
    "player_level": 15,
    "player_hp_pct": 0.469,
    "teammates_levels": [
      15,
      15,
      15,
      15
    ],
    "enemies_levels": [
      11,
      17,
      12
    ],
    "teammates_damage_taken": [
      0,
      0,
      0,
      0
    ],
    "enemies_damage_taken": [
      0,
      0,
      0
    ],
    "teammates_died": [
      false,
      false,
      false,
      false
    ],
    "enemies_died": [
      false,
      false,
      false
    ],
    "teammates_hp_pct": [
      0.908,
      0.898,
      0.642,
      1.0
    ],
    "enemies_hp_pct": [
      1.0,
      1.0,
      0.883
    ]
  }
}