{
  "1195.0": {
    "player_pos": [
      0.0,
      0.0
    ],
    "teammates_pos": [],
    "enemies_pos": [],
    "player_damage_taken": 0,
    "teammates_damage_taken": [],
    "enemies_damage_taken": [],
    "player_died": false,
    "teammates_died": [],
    "enemies_died": [],
    "player_level": 11,
    "teammates_levels": [],
    "enemies_levels": [],
    "player_hp_pct": 1.0,
    "teammates_hp_pct": [],
    "enemies_hp_pct": [],
    "player_incapacitated": false,
    "damage_events": []
  },
  "1196.0": {
    "player_pos": [
      0.0,
      0.0
    ],
    "teammates_pos": [],
    "enemies_pos": [],
    "player_damage_taken": 0,
    "teammates_damage_taken": [],
    "enemies_damage_taken": [],
    "player_died": false,
    "teammates_died": [],
    "enemies_died": [],
    "player_level": 11,
    "teammates_levels": [],
    "enemies_levels": [],
    "player_hp_pct": 1.0,
    "teammates_hp_pct": [],
    "enemies_hp_pct": [],
    "player_incapacitated": false,
    "damage_events": []
  },
  "1197.0": {
    "player_pos": [
      0.0,
      0.0
    ],
    "teammates_pos": [
      [
        -18.27,
        1.91
      ]
    ],
    "enemies_pos": [],
    "player_damage_taken": 0,
    "teammates_damage_taken": [
      0
    ],
    "enemies_damage_taken": [],
    "player_died": false,
    "teammates_died": [
      false
    ],
    "enemies_died": [],
    "player_level": 11,
    "teammates_levels": [
      11
    ],
    "enemies_levels": [],
    "player_hp_pct": 1.0,
    "teammates_hp_pct": [
      1.0
    ],
    "enemies_hp_pct": [],
    "player_incapacitated": false,
    "damage_events": []
  },
  "1198.0": {
    "player_pos": [
      0.0,
      0.0
    ],
    "teammates_pos": [
      [
        -17.29,
        3.81
      ]
    ],
    "enemies_pos": [],
    "player_damage_taken": 0,
    "teammates_damage_taken": [
      0
    ],
    "enemies_damage_taken": [],
    "player_died": false,
    "teammates_died": [
      false
    ],
    "enemies_died": [],
    "player_level": 11,
    "teammates_levels": [
      11
    ],
    "enemies_levels": [],
    "player_hp_pct": 1.0,
    "teammates_hp_pct": [
      1.0
    ],
    "enemies_hp_pct": [],
    "player_incapacitated": false,
    "damage_events": []
  },
  "1199.0": {
    "player_pos": [
      0.0,
      0.0
    ],
    "teammates_pos": [
      [
        -16.39,
        6.76
      ]
    ],
    "enemies_pos": [],
    "player_damage_taken": 0,
    "teammates_damage_taken": [
      0
    ],
    "enemies_damage_taken": [],
    "player_died": false,
    "teammates_died": [
      false
    ],
    "enemies_died": [],
    "player_level": 11,
    "teammates_levels": [
      11
    ],
    "enemies_levels": [],
    "player_hp_pct": 1.0,
    "teammates_hp_pct": [
      1.0
    ],
    "enemies_hp_pct": [],
    "player_incapacitated": false,
    "damage_events": []
  },
  "1200.0": {
    "player_pos": [
      0.0,
      0.0
    ],
    "teammates_pos": [
      [
        -13.41,
        10.13
      ]
    ],
    "enemies_pos": [],
    "player_damage_taken": 0,
    "teammates_damage_taken": [
      0
    ],
    "enemies_damage_taken": [],
    "player_died": false,
    "teammates_died": [
      false
    ],
    "enemies_died": [],
    "player_level": 11,
    "teammates_levels": [
      11
    ],
    "enemies_levels": [],
    "player_hp_pct": 1.0,
    "teammates_hp_pct": [
      1.0
    ],
    "enemies_hp_pct": [],
    "player_incapacitated": false,
    "damage_events": []
  },
  "1201.0": {
    "player_pos": [
      0.0,
      0.0
    ],
    "teammates_pos": [
      [
        -11.55,
        11.48
      ]
    ],
    "enemies_pos": [],
    "player_damage_taken": 0,
    "teammates_damage_taken": [
      0
    ],
    "enemies_damage_taken": [],
    "player_died": false,
    "teammates_died": [
      false
    ],
    "enemies_died": [],
    "player_level": 11,
    "teammates_levels": [
      11
    ],
    "enemies_levels": [],
    "player_hp_pct": 1.0,
    "teammates_hp_pct": [
      1.0
    ],
    "enemies_hp_pct": [],
    "player_incapacitated": false,
    "damage_events": []
  },
  "1202.0": {
    "player_pos": [
      0.0,
      0.0
    ],
    "teammates_pos": [
      [
        -12.05,
        11.42
      ]
    ],
    "enemies_pos": [],
    "player_damage_taken": 0,
    "teammates_damage_taken": [
      0
    ],
    "enemies_damage_taken": [],
    "player_died": false,
    "teammates_died": [
      false
    ],
    "enemies_died": [],
    "player_level": 11,
    "teammates_levels": [
      11
    ],
    "enemies_levels": [],
    "player_hp_pct": 1.0,
    "teammates_hp_pct": [
      1.0
    ],
    "enemies_hp_pct": [],
    "player_incapacitated": false,
    "damage_events": []
  },
  "1203.0": {
    "player_pos": [
      0.0,
      0.0
    ],
    "teammates_pos": [
      [
        -13.28,
        9.04
      ]
    ],
    "enemies_pos": [],
    "player_damage_taken": 9,
    "teammates_damage_taken": [
      0
    ],
    "enemies_damage_taken": [],
    "player_died": false,
    "teammates_died": [
      false
    ],
    "enemies_died": [],
    "player_level": 11,
    "teammates_levels": [
      11
    ],
    "enemies_levels": [],
    "player_hp_pct": 1.0,
    "teammates_hp_pct": [
      1.0
    ],
    "enemies_hp_pct": [],
    "player_incapacitated": false,
    "damage_events": []
  },
  "1204.0": {
    "player_pos": [
      0.0,
      0.0
    ],
    "teammates_pos": [
      [
        -14.28,
        6.24
      ]
    ],
    "enemies_pos": [],
    "player_damage_taken": 0,
    "teammates_damage_taken": [
      0
    ],
    "enemies_damage_taken": [],
    "player_died": false,
    "teammates_died": [
      false
    ],
    "enemies_died": [],
    "player_level": 11,
    "teammates_levels": [
      11
    ],
    "enemies_levels": [],
    "player_hp_pct": 1.0,
    "teammates_hp_pct": [
      1.0
    ],
    "enemies_hp_pct": [],
    "player_incapacitated": false,
    "damage_events": []
  },
  "1205.0": {
    "player_pos": [
      0.0,
      0.0
    ],
    "teammates_pos": [
      [
        -16.5,
        4.24
      ]
    ],
    "enemies_pos": [],
    "player_damage_taken": 18,
    "teammates_damage_taken": [
      0
    ],
    "enemies_damage_taken": [],
    "player_died": false,
    "teammates_died": [
      false
    ],
    "enemies_died": [],
    "player_level": 11,
    "teammates_levels": [
      11
    ],
    "enemies_levels": [],
    "player_hp_pct": 1.0,
    "teammates_hp_pct": [
      1.0
    ],
    "enemies_hp_pct": [],
    "player_incapacitated": false,
    "damage_events": []
  },
  "1206.0": {
    "player_pos": [
      0.0,
      0.0
    ],
    "teammates_pos": [
      [
        -18.77,
        2.81
      ]
    ],
    "enemies_pos": [],
    "player_damage_taken": 7,
    "teammates_damage_taken": [
      248
    ],
    "enemies_damage_taken": [],
    "player_died": false,
    "teammates_died": [
      false
    ],
    "enemies_died": [],
    "player_level": 11,
    "teammates_levels": [
      11
    ],
    "enemies_levels": [],
    "player_hp_pct": 0.987,
    "teammates_hp_pct": [
      1.0
    ],
    "enemies_hp_pct": [],
    "player_incapacitated": false,
    "damage_events": []
  },
  "1207.0": {
    "player_pos": [
      0.0,
      0.0
    ],
    "teammates_pos": [
      [
        -19.35,
        3.58
      ]
    ],
    "enemies_pos": [],
    "player_damage_taken": 0,
    "teammates_damage_taken": [
      0
    ],
    "enemies_damage_taken": [],
    "player_died": false,
    "teammates_died": [
      false
    ],
    "enemies_died": [],
    "player_level": 11,
    "teammates_levels": [
      11
    ],
    "enemies_levels": [],
    "player_hp_pct": 0.997,
    "teammates_hp_pct": [
      0.789
    ],
    "enemies_hp_pct": [],
    "player_incapacitated": false,
    "damage_events": []
  },
  "1208.0": {
    "player_pos": [
      0.0,
      0.0
    ],
    "teammates_pos": [
      [
        -18.49,
        2.49
      ]
    ],
    "enemies_pos": [
      [
        -13.42,
        3.75
      ]
    ],
    "player_damage_taken": 0,
    "teammates_damage_taken": [
      0
    ],
    "enemies_damage_taken": [
      0
    ],
    "player_died": false,
    "teammates_died": [
      false
    ],
    "enemies_died": [
      false
    ],
    "player_level": 11,
    "teammates_levels": [
      11
    ],
    "enemies_levels": [
      13
    ],
    "player_hp_pct": 1.0,
    "teammates_hp_pct": [
      0.793
    ],
    "enemies_hp_pct": [
      0.631
    ],
    "player_incapacitated": false,
    "damage_events": []
  },
  "1209.0": {
    "player_pos": [
      0.0,
      0.0
    ],
    "teammates_pos": [
      [
        -16.51,
        3.64
      ]
    ],
    "enemies_pos": [
      [
        -18.45,
        0.95
      ],
      [
        -3.95,
        1.76
      ]
    ],
    "player_damage_taken": 791,
    "teammates_damage_taken": [
      66
    ],
    "enemies_damage_taken": [
      30,
      0
    ],
    "player_died": false,
    "teammates_died": [
      false
    ],
    "enemies_died": [
      false,
      false
    ],
    "player_level": 11,
    "teammates_levels": [
      11
    ],
    "enemies_levels": [
      12,
      13
    ],
    "player_hp_pct": 1.0,
    "teammates_hp_pct": [
      0.797
    ],
    "enemies_hp_pct": [
      0.466,
      0.636
    ],
    "player_incapacitated": true,
    "damage_events": []
  },
  "1210.0": {
    "player_pos": [
      0.0,
      0.0
    ],
    "teammates_pos": [
      [
        -17.71,
        5.1
      ]
    ],
    "enemies_pos": [
      [
        -19.74,
        2.52
      ],
      [
        -2.24,
        1.51
      ]
    ],
    "player_damage_taken": 77,
    "teammates_damage_taken": [
      0
    ],
    "enemies_damage_taken": [
      30,
      0
    ],
    "player_died": false,
    "teammates_died": [
      false
    ],
    "enemies_died": [
      false,
      false
    ],
    "player_level": 11,
    "teammates_levels": [
      11
    ],
    "enemies_levels": [
      12,
      13
    ],
    "player_hp_pct": 0.18,
    "teammates_hp_pct": [
      0.756
    ],
    "enemies_hp_pct": [
      0.456,
      0.641
    ],
    "player_incapacitated": true,
    "damage_events": []
  }
}