{
  "1056.0": {
    "player_pos": [
      0.0,
      0.0
    ],
    "teammates_pos": [
      [
        -3.25,
        4.42
      ]
    ],
    "enemies_pos": [],
    "player_damage_taken": 0,
    "teammates_damage_taken": [
      0
    ],
    "enemies_damage_taken": [],
    "player_died": false,
    "teammates_died": [
      false
    ],
    "enemies_died": [],
    "player_level": 6,
    "teammates_levels": [
      10
    ],
    "enemies_levels": [],
    "player_hp_pct": 0,
    "teammates_hp_pct": [
      0
    ],
    "enemies_hp_pct": [],
    "player_incapacitated": false,
    "damage_events": []
  },
  "1057.0": {
    "player_pos": [
      0.0,
      0.0
    ],
    "teammates_pos": [
      [
        10.28,
        6.82
      ]
    ],
    "enemies_pos": [
      [
        -4.22,
        -3.25
      ]
    ],
    "player_damage_taken": 11,
    "teammates_damage_taken": [
      0
    ],
    "enemies_damage_taken": [
      191
    ],
    "player_died": false,
    "teammates_died": [
      false
    ],
    "enemies_died": [
      false
    ],
    "player_level": 6,
    "teammates_levels": [
      11
    ],
    "enemies_levels": [
      12
    ],
    "player_hp_pct": 0,
    "teammates_hp_pct": [
      0
    ],
    "enemies_hp_pct": [
      0
    ],
    "player_incapacitated": false,
    "damage_events": []
  },
  "1058.0": {
    "player_pos": [
      0.0,
      0.0
    ],
    "teammates_pos": [
      [
        10.5,
        6.99
      ]
    ],
    "enemies_pos": [
      [
        -4.0,
        -3.08
      ]
    ],
    "player_damage_taken": 23,
    "teammates_damage_taken": [
      0
    ],
    "enemies_damage_taken": [
      45
    ],
    "player_died": false,
    "teammates_died": [
      false
    ],
    "enemies_died": [
      false
    ],
    "player_level": 6,
    "teammates_levels": [
      11
    ],
    "enemies_levels": [
      12
    ],
    "player_hp_pct": 0,
    "teammates_hp_pct": [
      0
    ],
    "enemies_hp_pct": [
      0
    ],
    "player_incapacitated": false,
    "damage_events": []
  },
  "1059.0": {
    "player_pos": [
      0.0,
      0.0
    ],
    "teammates_pos": [
      [
        11.15,
        7.19
      ],
      [
        7.05,
        11.92
      ]
    ],
    "enemies_pos": [
      [
        -3.35,
        -2.88
      ]
    ],
    "player_damage_taken": 583,
    "teammates_damage_taken": [
      0,
      0
    ],
    "enemies_damage_taken": [
      75
    ],
    "player_died": false,
    "teammates_died": [
      false,
      false
    ],
    "enemies_died": [
      false
    ],
    "player_level": 6,
    "teammates_levels": [
      11,
      10
    ],
    "enemies_levels": [
      12
    ],
    "player_hp_pct": 0,
    "teammates_hp_pct": [
      0,
      0
    ],
    "enemies_hp_pct": [
      0
    ],
    "player_incapacitated": false,
    "damage_events": []
  },
  "1060.0": {
    "player_pos": [
      0.0,
      0.0
    ],
    "teammates_pos": [
      [
        14.98,
        9.33
      ],
      [
        8.93,
        12.32
      ]
    ],
    "enemies_pos": [
      [
        0.83,
        -0.44
      ]
    ],
    "player_damage_taken": 11,
    "teammates_damage_taken": [
      0,
      0
    ],
    "enemies_damage_taken": [
      45
    ],
    "player_died": false,
    "teammates_died": [
      false,
      false
    ],
    "enemies_died": [
      false
    ],
    "player_level": 6,
    "teammates_levels": [
      11,
      10
    ],
    "enemies_levels": [
      12
    ],
    "player_hp_pct": 0,
    "teammates_hp_pct": [
      0,
      0
    ],
    "enemies_hp_pct": [
      0
    ],
    "player_incapacitated": false,
    "damage_events": []
  },
  "1061.0": {
    "player_pos": [
      0.0,
      0.0
    ],
    "teammates_pos": [
      [
        14.98,
        9.33
      ],
      [
        6.84,
        10.75
      ]
    ],
    "enemies_pos": [
      [
        0.8,
        -0.3
      ]
    ],
    "player_damage_taken": 12,
    "teammates_damage_taken": [
      0,
      0
    ],
    "enemies_damage_taken": [
      72
    ],
    "player_died": false,
    "teammates_died": [
      false,
      false
    ],
    "enemies_died": [
      false
    ],
    "player_level": 6,
    "teammates_levels": [
      11,
      10
    ],
    "enemies_levels": [
      12
    ],
    "player_hp_pct": 0,
    "teammates_hp_pct": [
      0,
      0
    ],
    "enemies_hp_pct": [
      0
    ],
    "player_incapacitated": false,
    "damage_events": []
  },
  "1062.0": {
    "player_pos": [
      0.0,
      0.0
    ],
    "teammates_pos": [
      [
        14.98,
        9.33
      ],
      [
        5.17,
        8.77
      ]
    ],
    "enemies_pos": [
      [
        0.57,
        0.77
      ]
    ],
    "player_damage_taken": 12,
    "teammates_damage_taken": [
      0,
      0
    ],
    "enemies_damage_taken": [
      368
    ],
    "player_died": false,
    "teammates_died": [
      false,
      false
    ],
    "enemies_died": [
      false
    ],
    "player_level": 7,
    "teammates_levels": [
      11,
      10
    ],
    "enemies_levels": [
      12
    ],
    "player_hp_pct": 0,
    "teammates_hp_pct": [
      0,
      0
    ],
    "enemies_hp_pct": [
      0
    ],
    "player_incapacitated": false,
    "damage_events": []
  },
  "1063.0": {
    "player_pos": [
      0.0,
      0.0
    ],
    "teammates_pos": [
      [
        14.98,
        9.33
      ],
      [
        4.83,
        8.26
      ]
    ],
    "enemies_pos": [
      [
        0.37,
        1.73
      ]
    ],
    "player_damage_taken": 245,
    "teammates_damage_taken": [
      0,
      0
    ],
    "enemies_damage_taken": [
      62
    ],
    "player_died": false,
    "teammates_died": [
      false,
      false
    ],
    "enemies_died": [
      false
    ],
    "player_level": 7,
    "teammates_levels": [
      11,
      10
    ],
    "enemies_levels": [
      12
    ],
    "player_hp_pct": 0,
    "teammates_hp_pct": [
      0,
      0
    ],
    "enemies_hp_pct": [
      0
    ],
    "player_incapacitated": true,
    "damage_events": []
  },
  "1064.0": {
    "player_pos": [
      0.0,
      0.0
    ],
    "teammates_pos": [
      [
        14.98,
        9.33
      ],
      [
        2.21,
        4.4
      ]
    ],
    "enemies_pos": [
      [
        1.95,
        3.99
      ]
    ],
    "player_damage_taken": 0,
    "teammates_damage_taken": [
      0,
      0
    ],
    "enemies_damage_taken": [
      328
    ],
    "player_died": false,
    "teammates_died": [
      false,
      false
    ],
    "enemies_died": [
      false
    ],
    "player_level": 7,
    "teammates_levels": [
      11,
      10
    ],
    "enemies_levels": [
      12
    ],
    "player_hp_pct": 0,
    "teammates_hp_pct": [
      0,
      0
    ],
    "enemies_hp_pct": [
      0
    ],
    "player_incapacitated": true,
    "damage_events": []
  },
  "1065.0": {
    "player_pos": [
      0.0,
      0.0
    ],
    "teammates_pos": [
      [
        14.98,
        9.33
      ],
      [
        1.88,
        4.11
      ]
    ],
    "enemies_pos": [
      [
        0.55,
        2.09
      ]
    ],
    "player_damage_taken": 215,
    "teammates_damage_taken": [
      0,
      0
    ],
    "enemies_damage_taken": [
      786
    ],
    "player_died": false,
    "teammates_died": [
      false,
      false
    ],
    "enemies_died": [
      false
    ],
    "player_level": 7,
    "teammates_levels": [
      11,
      10
    ],
    "enemies_levels": [
      12
    ],
    "player_hp_pct": 0,
    "teammates_hp_pct": [
      0,
      0
    ],
    "enemies_hp_pct": [
      0
    ],
    "player_incapacitated": false,
    "damage_events": []
  },
  "1066.0": {
    "player_pos": [
      0.0,
      0.0
    ],
    "teammates_pos": [
      [
        14.98,
        9.33
      ],
      [
        1.88,
        4.11
      ]
    ],
    "enemies_pos": [
      [
        0.36,
        1.45
      ]
    ],
    "player_damage_taken": 103,
    "teammates_damage_taken": [
      0,
      0
    ],
    "enemies_damage_taken": [
      276
    ],
    "player_died": true,
    "teammates_died": [
      false,
      false
    ],
    "enemies_died": [
      false
    ],
    "player_level": 7,
    "teammates_levels": [
      11,
      10
    ],
    "enemies_levels": [
      12
    ],
    "player_hp_pct": 0,
    "teammates_hp_pct": [
      0,
      0
    ],
    "enemies_hp_pct": [
      0
    ],
    "player_incapacitated": false,
    "damage_events": []
  }
}